djutils_common/__init__.py
djutils_common-0.1.0.dev0.dist-info/LICENSE
djutils_common-0.1.0.dev0.dist-info/METADATA
djutils_common-0.1.0.dev0.dist-info/WHEEL
djutils_common-0.1.0.dev0.dist-info/top_level.txt
djutils_common-0.1.0.dev0.dist-info/RECORD
